mule/__init__.py
mule/analysis.py
mule/cli/__init__.py
mule/cli/cli.py
mule/cli/options.py
mule/extractors/__init__.py
mule/extractors/block_extractor.py
mule/extractors/extractor.py
mule/extractors/slice_extractor.py
mule/features/__init__.py
mule/features/feature.py
mule/features/source_features/__init__.py
mule/features/source_features/audio_waveform.py
mule/features/source_features/source_feature.py
mule/features/transform_features/__init__.py
mule/features/transform_features/embedding_feature.py
mule/features/transform_features/mel_spectrogram.py
mule/features/transform_features/transform_feature.py
mule/models/__init__.py
mule/models/mlp.py
mule/models/model.py
mule/models/sfnfnetf0.py
mule/models/layers/__init__.py
mule/models/layers/scalar_multiply.py
mule/models/layers/stoch_depth.py
mule/models/layers/weight_standardization.py
mule/models/losses/__init__.py
mule/models/losses/loss.py
mule/models/losses/sim_clr_loss.py
mule/models/metrics/__init__.py
mule/models/metrics/train_metric.py
mule/models/optimizers/__init__.py
mule/models/optimizers/optimizer.py
mule/models/optimizers/schedules/__init__.py
mule/models/optimizers/schedules/lr_schedule.py
mule/models/optimizers/schedules/warmup_schedule.py
mule/source_files/__init__.py
mule/source_files/audio_file.py
mule/source_files/source_file.py
sxmp_mule-1.0.1.dist-info/LICENSE
sxmp_mule-1.0.1.dist-info/METADATA
sxmp_mule-1.0.1.dist-info/WHEEL
sxmp_mule-1.0.1.dist-info/entry_points.txt
sxmp_mule-1.0.1.dist-info/top_level.txt
sxmp_mule-1.0.1.dist-info/RECORD
