Metadata-Version: 2.1
Name: sxmp-mule
Version: 1.0.1
Home-page: https://github.com/PandoraMedia/music-audio-representations
Author: Matt C. McCallum
Author-email: mmccallum@pandora.com
License: GNU GPL 3.0
Project-URL: Documentation, https://github.com/PandoraMedia/music-audio-representations
Project-URL: Bug Reports, https://github.com/PandoraMedia/music-audio-representations/issues
Project-URL: Source, https://github.com/PandoraMedia/music-audio-representations
Keywords: mule audio music embeddings machine learning
Classifier: Development Status :: 3 - Alpha
Classifier: Intended Audience :: Education
Classifier: Intended Audience :: Science/Research
Classifier: License :: OSI Approved :: GNU General Public License v3 (GPLv3)
Classifier: Programming Language :: Python :: 3.8
Classifier: Programming Language :: Python :: 3.9
Classifier: Programming Language :: Python :: 3.10
Classifier: Topic :: Scientific/Engineering
Classifier: Topic :: Scientific/Engineering :: Mathematics
Classifier: Topic :: Scientific/Engineering :: Artificial Intelligence
Classifier: Topic :: Multimedia :: Sound/Audio :: Analysis
Requires-Python: >=3.8
License-File: LICENSE
Requires-Dist: numpy
Requires-Dist: librosa
Requires-Dist: click (==8.0.0a1)
Requires-Dist: scooch (>=1.0.0)
Requires-Dist: tensorflow (==2.9.1)
